freegsnke/GSstaticsolver.py
freegsnke/Myy_builder.py
freegsnke/__init__.py
freegsnke/build_machine.py
freegsnke/circuit_eq_metal.py
freegsnke/circuit_eq_plasma.py
freegsnke/copying.py
freegsnke/equilibrium_update.py
freegsnke/implicit_euler.py
freegsnke/inverse.py
freegsnke/jtor_refinement.py
freegsnke/jtor_update.py
freegsnke/limiter_func.py
freegsnke/linear_solve.py
freegsnke/machine_config.py
freegsnke/machine_update.py
freegsnke/magnetic_probes.py
freegsnke/mastu_tools.py
freegsnke/nk_solver_H.py
freegsnke/nonlinear_solve.py
freegsnke/normal_modes.py
freegsnke/passive_structure.py
freegsnke/refine_passive.py
freegsnke/simplified_solve.py
freegsnke/switch_profile.py
freegsnke/virtual_circuits.py
freegsnke-2.1.0.dist-info/licenses/LICENSE
freegsnke-2.1.0.dist-info/METADATA
freegsnke-2.1.0.dist-info/WHEEL
freegsnke-2.1.0.dist-info/top_level.txt
freegsnke-2.1.0.dist-info/RECORD
