Metadata-Version: 2.4
Name: freegsnke
Version: 2.1.0
Summary: FreeGSNKE: A Python code for evolutive free-boundary tokamak plasma equilibrium simulations
Author: The FreeGSNKE Developers
Project-URL: Homepage, https://github.com/FusionComputingLab/freegsnke
Classifier: Programming Language :: Python :: 3
Classifier: Operating System :: OS Independent
Classifier: License :: OSI Approved :: GNU Lesser General Public License v3 (LGPLv3)
Requires-Python: >=3.9
License-File: LICENSE
Requires-Dist: scipy~=1.15.3
Requires-Dist: numpy~=1.26.4
Requires-Dist: matplotlib~=3.10.3
Requires-Dist: h5py~=3.13.0
Requires-Dist: deepdiff~=7.0.1
Requires-Dist: scikit-image~=0.25.2
Requires-Dist: notebook~=7.4.2
Provides-Extra: dev
Requires-Dist: build; extra == "dev"
Requires-Dist: twine; extra == "dev"
Requires-Dist: pytest; extra == "dev"
Requires-Dist: pre-commit; extra == "dev"
Requires-Dist: black==24.3.0; extra == "dev"
Requires-Dist: isort==5.13.2; extra == "dev"
Provides-Extra: freegs4e
Requires-Dist: freegs4e~=0.12; extra == "freegs4e"
Provides-Extra: uda
Requires-Dist: uda; extra == "uda"
Provides-Extra: docs
Requires-Dist: sphinx==8.1.3; extra == "docs"
Requires-Dist: sphinx-math-dollar==1.2.1; extra == "docs"
Requires-Dist: sphinx-rtd-dark-mode==1.3.0; extra == "docs"
Requires-Dist: sphinx-rtd-theme==3.0.2; extra == "docs"
Requires-Dist: sphinx-autobuild==2024.10.03; extra == "docs"
Requires-Dist: ipython==8.36.0; extra == "docs"
Requires-Dist: m2r2==0.3.4; extra == "docs"
Requires-Dist: myst-nb==1.2.0; extra == "docs"
Requires-Dist: docutils==0.21.2; extra == "docs"
Requires-Dist: mistune==0.8.4; extra == "docs"
Requires-Dist: lxml_html_clean==0.4.2; extra == "docs"
Dynamic: license-file
